qlearnkit/__init__.py
qlearnkit/_version.py
qlearnkit/optionals.py
qlearnkit/version.py
qlearnkit/algorithms/__init__.py
qlearnkit/algorithms/kernel_method_mixin.py
qlearnkit/algorithms/quantum_estimator.py
qlearnkit/algorithms/qkmeans/__init__.py
qlearnkit/algorithms/qkmeans/centroid_initialization.py
qlearnkit/algorithms/qkmeans/qkmeans.py
qlearnkit/algorithms/qkmeans/qkmeans_circuit.py
qlearnkit/algorithms/qknn/__init__.py
qlearnkit/algorithms/qknn/qknn_base.py
qlearnkit/algorithms/qknn/qknn_classifier.py
qlearnkit/algorithms/qknn/qknn_regressor.py
qlearnkit/algorithms/qridge/__init__.py
qlearnkit/algorithms/qridge/qridge.py
qlearnkit/algorithms/qsvm/__init__.py
qlearnkit/algorithms/qsvm/qsvc.py
qlearnkit/circuits/__init__.py
qlearnkit/circuits/circuit_utils.py
qlearnkit/circuits/swap_test_circuit.py
qlearnkit/datasets/__init__.py
qlearnkit/datasets/breast_cancer.py
qlearnkit/datasets/dataset_helper.py
qlearnkit/datasets/iris.py
qlearnkit/datasets/wine.py
qlearnkit/encodings/__init__.py
qlearnkit/encodings/amplitude_encoding.py
qlearnkit/encodings/angle_encoding.py
qlearnkit/encodings/basis_encoding.py
qlearnkit/encodings/encoding_map.py
qlearnkit/nn/__init__.py
qlearnkit/nn/qrnn.py
qlearnkit-0.2.0.dist-info/LICENSE
qlearnkit-0.2.0.dist-info/METADATA
qlearnkit-0.2.0.dist-info/WHEEL
qlearnkit-0.2.0.dist-info/top_level.txt
qlearnkit-0.2.0.dist-info/RECORD
