Metadata-Version: 2.1
Name: qlearnkit
Version: 0.2.0
Summary: UNKNOWN
Home-page: https://github.com/mspronesti/qlearnkit
Author: Massimiliano Pronesti, Federico Tiblias, Giulio Corallo
License: UNKNOWN
Platform: UNKNOWN
Requires-Python: >=3.7
License-File: LICENSE
Requires-Dist: qiskit-terra (>=0.20.0)
Requires-Dist: qiskit-aer (>=0.10.3)
Requires-Dist: qiskit-machine-learning (>=0.3.1)
Requires-Dist: scikit-learn (==1.0.2)
Requires-Dist: scipy (==1.7.3)
Requires-Dist: numpy (==1.21.5)
Provides-Extra: pennylane
Requires-Dist: pennylane ; extra == 'pennylane'
Requires-Dist: torch ; extra == 'pennylane'
